{
  "head": {
    "tick": 0
  },
  "signal": [{
      "name": ["tspan", {
        "class": "h3",
        "fill": "black",
        "font-weight": "bold"
      }, "clk"],
      "wave": "n...........",
      "period": 1
    },
    {
      "name": ["tspan", {
        "class": "h3",
        "fill": "black",
        "font-weight": "bold"
      }, "poly_bcd[7:0]"],
      "wave": "3...........",
      "data": [
        ["tspan", {
          "class": "h4"
        }, "b'00000110"]
      ]
    },
    {
      "name": ["tspan", {
        "class": "h3",
        "fill": "black",
        "font-weight": "bold"
      }, "mask[8:0]"],
      "wave": "3...........",
      "data": [
        ["tspan", {
          "class": "h4"
        }, "b'000000111"]
      ]
    },
    {
      "name": ["tspan", {
        "class": "h3",
        "fill": "black",
        "font-weight": "bold"
      }, "msb[2:0]"],
      "wave": "3...........",
      "data": [
        ["tspan", {
          "class": "h4"
        }, "2"]
      ]
    },
    {
      "name": ["tspan", {
        "class": "h3",
        "fill": "black",
        "font-weight": "bold"
      }, "en"],
      "wave": "01.........."
    },
    {
      "name": ["tspan", {
        "class": "h3",
        "fill": "black",
        "font-weight": "bold"
      }, "rst"],
      "wave": "1.0........."
    },
    {
      "name": ["tspan", {
        "class": "h3",
        "fill": "black",
        "font-weight": "bold"
      }, "id_gen"],
      "wave": "0..1...............0....",
      "period": 0.5
    },
    {
      "name": ["tspan", {
        "class": "h3",
        "fill": "black",
        "font-weight": "bold"
      }, "gen_rdy"],
      "wave": "0..................1....",
      "period": 0.5
    },
    {
      "name": ["tspan", {
        "class": "h3",
        "fill": "black",
        "font-weight": "bold"
      }, "mem_rdy"],
      "wave": "n...........",
      "period": 1
    },
    {
      "name": ["tspan", {
        "class": "h3",
        "fill": "black",
        "font-weight": "bold"
      }, "addr_gen[8:0]"],
      "wave": "x..2.3.4.2.3.4.2.3......",
      "period": 0.5,
      "data": [
        ["tspan", {
          "class": "h4"
        }, "0"],
        ["tspan", {
          "class": "h4"
        }, "1"],
        ["tspan", {
          "class": "h4"
        }, "2"],
        ["tspan", {
          "class": "h4"
        }, "3"],
        ["tspan", {
          "class": "h4"
        }, "4"],
        ["tspan", {
          "class": "h4"
        }, "5"],
        ["tspan", {
          "class": "h4"
        }, "6"],
        ["tspan", {
          "class": "h4"
        }, "NULL"]
      ]
    },
    {
      "name": ["tspan", {
        "class": "h3",
        "fill": "black",
        "font-weight": "bold"
      }, "elem[8:0]"],
      "wave": "x..2.3.4.2.3.4.2.3......",
      "period": 0.5,
      "data": [
        ["tspan", {
          "class": "h4"
        }, "1"],
        ["tspan", {
          "class": "h4"
        }, "2"],
        ["tspan", {
          "class": "h4"
        }, "4"],
        ["tspan", {
          "class": "h4"
        }, "5"],
        ["tspan", {
          "class": "h4"
        }, "7"],
        ["tspan", {
          "class": "h4"
        }, "3"],
        ["tspan", {
          "class": "h4"
        }, "6"],
        ["tspan", {
          "class": "h4"
        }, "0"]
      ]
    }
  ]
}